{
  "code": 0,
  "msg": "",
  "count": 100,
  "data": [{
      "param1": "济南",
      "param2": 1231423,
      "param3": 345234,
      "param4": 1534523,
      "param5": 345,
      "param6": 12
    },
    {
      "param1": "济南",
      "param2": 1231423,
      "param3": 345234,
      "param4": 1534523,
      "param5": 345,
      "param6": 12
    },
    {
      "param1": "济南",
      "param2": 1231423,
      "param3": 345234,
      "param4": 1534523,
      "param5": 345,
      "param6": 12
    },
    {
      "param1": "济南",
      "param2": 1231423,
      "param3": 345234,
      "param4": 1534523,
      "param5": 345,
      "param6": 12
    },
    {
      "param1": "济南",
      "param2": 1231423,
      "param3": 345234,
      "param4": 1534523,
      "param5": 345,
      "param6": 12
    },
    {
      "param1": "济南",
      "param2": 1231423,
      "param3": 345234,
      "param4": 1534523,
      "param5": 345,
      "param6": 12
    },
    {
      "param1": "济南",
      "param2": 1231423,
      "param3": 345234,
      "param4": 1534523,
      "param5": 345,
      "param6": 12
    },
    {
      "param1": "济南",
      "param2": 1231423,
      "param3": 345234,
      "param4": 1534523,
      "param5": 345,
      "param6": 12
    },
    {
      "param1": "济南",
      "param2": 1231423,
      "param3": 345234,
      "param4": 1534523,
      "param5": 345,
      "param6": 12
    },
    {
      "param1": "济南",
      "param2": 1231423,
      "param3": 345234,
      "param4": 1534523,
      "param5": 345,
      "param6": 12
    }
  ]
}